mgcpy/__init__.py
mgcpy/benchmarks/__init__.py
mgcpy/benchmarks/figure_2_power_curve.py
mgcpy/benchmarks/power.py
mgcpy/benchmarks/power_two_sample.py
mgcpy/benchmarks/simulations.py
mgcpy/benchmarks/hypothesis_tests/__init__.py
mgcpy/benchmarks/hypothesis_tests/three_sample_test/__init__.py
mgcpy/benchmarks/hypothesis_tests/three_sample_test/generate_power_curve.py
mgcpy/benchmarks/hypothesis_tests/three_sample_test/power.py
mgcpy/benchmarks/hypothesis_tests/three_sample_test/python_power_curves_epsilon/__init__.py
mgcpy/benchmarks/hypothesis_tests/two_sample_test/__init__.py
mgcpy/benchmarks/hypothesis_tests/two_sample_test/generate_power_curve.py
mgcpy/benchmarks/hypothesis_tests/two_sample_test/power.py
mgcpy/benchmarks/hypothesis_tests/two_sample_test/python_power_curves_sample_size/__init__.py
mgcpy/benchmarks/hypothesis_tests/two_sample_test/sample_data_power_sample_sizes/__init__.py
mgcpy/benchmarks/hypothesis_tests/two_sample_test/sample_data_viz/__init__.py
mgcpy/benchmarks/unit_tests/__init__.py
mgcpy/benchmarks/unit_tests/power_test.py
mgcpy/benchmarks/unit_tests/simulations_test.py
mgcpy/hypothesis_tests/__init__.py
mgcpy/hypothesis_tests/transforms.py
mgcpy/hypothesis_tests/unit_test.py
mgcpy/independence_tests/__init__.py
mgcpy/independence_tests/abstract_class.py
mgcpy/independence_tests/dcorr.py
mgcpy/independence_tests/dcorrx.py
mgcpy/independence_tests/hhg.py
mgcpy/independence_tests/kendall_spearman.py
mgcpy/independence_tests/manova.py
mgcpy/independence_tests/mdmr.py
mgcpy/independence_tests/mgc.py
mgcpy/independence_tests/mgcx.py
mgcpy/independence_tests/rv_corr.py
mgcpy/independence_tests/mgc_utils/__init__.py
mgcpy/independence_tests/mgc_utils/local_correlation.cpython-37m-darwin.so
mgcpy/independence_tests/mgc_utils/threshold_smooth.py
mgcpy/independence_tests/unit_tests/__init__.py
mgcpy/independence_tests/unit_tests/hhg_test.py
mgcpy/independence_tests/unit_tests/kendall_spearman_test.py
mgcpy/independence_tests/unit_tests/manova_test.py
mgcpy-0.4.0.dist-info/LICENSE
mgcpy-0.4.0.dist-info/METADATA
mgcpy-0.4.0.dist-info/WHEEL
mgcpy-0.4.0.dist-info/top_level.txt
mgcpy-0.4.0.dist-info/RECORD
