Metadata-Version: 2.1
Name: mgcpy
Version: 0.4.0
Summary: A set of tools in Python for multiscale graph correlation and other statistical tests
Home-page: https://github.com/neurodata/mgcpy
Author: Satish Palaniappan, Bear Xiong, Sambit Panda, Sandhya Ramachandran, Ananya Swaminathan, Richard Guo
Author-email: spalani2@jhu.edu
License: Apache License 2.0
Platform: UNKNOWN
Classifier: Development Status :: 3 - Alpha
Classifier: Intended Audience :: Science/Research
Classifier: Topic :: Scientific/Engineering :: Mathematics
Classifier: License :: OSI Approved :: Apache Software License
Classifier: Programming Language :: Python :: 3
Classifier: Programming Language :: Python :: 3.4
Classifier: Programming Language :: Python :: 3.5
Classifier: Programming Language :: Python :: 3.6
Classifier: Programming Language :: Python :: 3.7
Requires-Dist: numpy (>=1.14.5)
Requires-Dist: scipy (>=1.1.0)
Requires-Dist: h5py (>=2.7.1)
Requires-Dist: Cython (==0.29)
Requires-Dist: scikit-learn (>=0.19.2)
Requires-Dist: pandas (>=0.23.4)
